lair3/__init__.py
lair3/address_walk.py
lair3/http_packet.py
lair3/securesocket.py
lair3/sockets.py
lair3/x509.py
lair3-0.2.9.dist-info/LICENSE
lair3-0.2.9.dist-info/METADATA
lair3-0.2.9.dist-info/WHEEL
lair3-0.2.9.dist-info/top_level.txt
lair3-0.2.9.dist-info/RECORD
